{
    "projects": [
        {
            "id": "6dcf9df2-fd44-4947-b201-6515b9b20af1",
            "name": "Dashboard sur le Forecast",
            "levels": [
                {
                    "id": "43bb4a1b-da0b-4ff6-8b37-2efc566c0fa0",
                    "name": "ERP",
                    "description": "Analyser l'ERP",
                    "nextLevelId": "88f4cafc-5ae2-409d-8d77-dbfd5a74ad04",
                    "steps": [
                        {
                            "id": "034c2a78-aed7-429a-9965-567a1e148bc5",
                            "name": "Code source",
                            "description": "Avoir accès au code source de l'ERP",
                            "done": false
                        },
                        {
                            "id": "66aed063-069b-4d48-a450-67cadc8cd422",
                            "name": "Environnement de dev",
                            "description": "Installer un environnement de développement",
                            "done": false
                        },
                        {
                            "id": "dd39a5aa-7316-4158-b672-81692709a574",
                            "name": "Fonctionnement",
                            "description": "Comprendre le fonctionnement de l'application en testant des choses, en demandant aux utilisateurs finaux et/ou aux développeurs en charge, etc.",
                            "done": false
                        },
                        {
                            "id": "33c1b87a-5764-454a-bf3a-ba8df5654567",
                            "name": "Documenter",
                            "description": "Écrire une documentation sur le fonctionnement de l'application",
                            "done": false
                        }
                    ]
                },
                {
                    "id": "88f4cafc-5ae2-409d-8d77-dbfd5a74ad04",
                    "name": "cAUTHpyx",
                    "description": "Analyser cAUTHpyx",
                    "reward": "1 pâtisserie au choix",
                    "previousLevelId": "43bb4a1b-da0b-4ff6-8b37-2efc566c0fa0",
                    "nextLevelId": "8e27602f-c9cf-4d63-bb6e-60dd442926e7",
                    "steps": [
                        {
                            "id": "650f031d-4a99-4b2d-acc3-cc18a57dc7b5",
                            "name": "Code source",
                            "description": "Avoir accès au code source de cAUTHpyx",
                            "done": false
                        },
                        {
                            "id": "fb620796-5196-4814-a751-6013a2f9c981",
                            "name": "Environnement de dev",
                            "description": "Installer un environnement de développement",
                            "done": false
                        },
                        {
                            "id": "5b7c5166-4426-4ce2-a52b-d62a1887b89a",
                            "name": "Fonctionnement",
                            "description": "Comprendre le fonctionnement de l'application en testant des choses, en demandant aux utilisateurs finaux et/ou aux développeurs en charge, etc.",
                            "done": false
                        },
                        {
                            "id": "24a90baf-331e-429b-bb00-9124f3788375",
                            "name": "Documenter",
                            "description": "Écrire une documentation sur le fonctionnement de l'application",
                            "done": false
                        }
                    ]
                },
                {
                    "id": "8e27602f-c9cf-4d63-bb6e-60dd442926e7",
                    "name": "Documents extérieurs",
                    "description": "Analyser les documents extérieurs à l'ERP",
                    "reward": "1 dîner (fast-food/pizzeria)",
                    "previousLevelId": "88f4cafc-5ae2-409d-8d77-dbfd5a74ad04",
                    "nextLevelId": "fe62557e-482c-465a-8a23-009774e347f7",
                    "steps": [
                        {
                            "id": "5109b348-d365-406e-aede-a58a903b8833",
                            "name": "ERP",
                            "description": "Analyser et documenter les documents et informations venant de l'ERP",
                            "done": false
                        },
                        {
                            "id": "78f12dbe-d08d-46f1-aeda-3c6ed3e02b3c",
                            "name": "Autre",
                            "description": "Analyser et documenter les documents et informations venant d'ailleurs",
                            "done": false
                        }
                    ]
                },
                {
                    "id": "fe62557e-482c-465a-8a23-009774e347f7",
                    "name": "Dashboard sur le Forecast: partie 1",
                    "description": "Analyser le projet à réaliser",
                    "reward": "1 restaurant",
                    "previousLevelId": "8e27602f-c9cf-4d63-bb6e-60dd442926e7",
                    "nextLevelId": "17c3b8a9-00b7-4cec-b519-79a10769f247",
                    "steps": [
                        {
                            "id": "ca7c93fb-5b7c-40eb-95d9-d2ef43eb0ff2",
                            "name": "Besoins",
                            "description": "Parler au(x) client(s) et comprendre les besoins. Comprendre comment la solution actuelle répond à la problématique, et comment l'automatiser peut être plus efficace.",
                            "done": false
                        },
                        {
                            "id": "976e1ef3-8f9e-46a0-a3d5-d3332373bc77",
                            "name": "Documenter",
                            "description": "Écrire un document expliquant les besoins et nécessités",
                            "done": false
                        },
                        {
                            "id": "5b83a105-222a-4848-8640-897beb8cda9a",
                            "name": "Écrans",
                            "description": "Réaliser des sketchs et maquettes d'écran",
                            "done": false
                        }
                    ]
                },
                {
                    "id": "17c3b8a9-00b7-4cec-b519-79a10769f247",
                    "name": "Dashboard sur le Forecast: partie 2",
                    "description": "Développer le projet",
                    "reward": "1 carte-cadeau de 50€",
                    "previousLevelId": "fe62557e-482c-465a-8a23-009774e347f7",
                    "nextLevelId": "c888761c-f3c5-4ecb-8e26-d5628ed1940b",
                    "steps": [
                        {
                            "id": "e0fb9c88-31e4-41ea-986a-76c98f5fbcca",
                            "name": "Technologie",
                            "description": "Choisir la technologie et argumenter son choix",
                            "done": false,
                            "optional": true
                        },
                        {
                            "id": "1435b4a2-f964-4af6-9206-dcdf4dbf5350",
                            "name": "Fonctionnalités",
                            "description": "Définir les fonctionnalités et avancer en mode Agile (réanalyser/analyser en profondeur chaque fonctionnalité du sprint)",
                            "done": false
                        },
                        {
                            "id": "165afd40-692a-4ab1-af83-2071ae397ff1",
                            "name": "Dev",
                            "description": "Développer les fonctionnalités",
                            "done": false
                        },
                        {
                            "id": "e674d1ee-6ac5-41a5-aa19-67c4fc6a726f",
                            "name": "Test",
                            "description": "Tester les fonctionnalités (unit testing)",
                            "done": false,
                            "optional": true
                        },
                        {
                            "id": "cc5ed860-f32d-4edb-a3d8-4a45599bdd76",
                            "name": "Démo",
                            "description": "Faire une démonstration des avancées du développement",
                            "done": false
                        }
                    ]
                },
                {
                    "id": "c888761c-f3c5-4ecb-8e26-d5628ed1940b",
                    "name": "Dashboard sur le forecast: partie 3",
                    "description": "Réaliser une documentation complète",
                    "reward": "1 week-end 'wonderbox'",
                    "previousLevelId": "17c3b8a9-00b7-4cec-b519-79a10769f247",
                    "steps": [
                        {
                            "id": "aef392ce-a160-4dc5-92a5-4b4ace9dde4c",
                            "name": "Structurer",
                            "description": "Structurer convenablement sa documentation avec une table des matières, une introduction, un contenu principal et une conclusion.",
                            "done": false
                        },
                        {
                            "id": "1628a73b-d803-461d-8170-7df644e2ff03",
                            "name": "Écrire",
                            "description": "Assembler toutes les informations documentés jusqu'à présent dans un document qui a du sens. Ajouter du contenu si nécessaire, restructurer, paraphraser, etc.",
                            "done": false
                        },
                        {
                            "id": "8147456b-a3e8-451d-8a09-2ede60cabc96",
                            "name": "Images et exemples",
                            "description": "Fournir des exemples (concrets ou imagés), des images et autres informations pouvant éclairer des points complexes.",
                            "done": false
                        },
                        {
                            "id": "40feab9c-6c03-41a5-a8ed-dd5ae9bafdfd",
                            "name": "Relecture",
                            "description": "Faire relire et vérifier le document par son maître de stage",
                            "done": false,
                            "optional": true
                        }
                    ]
                }
            ]
        }
    ]
}